README.md
setup.py
pypprof/__init__.py
pypprof/builder.py
pypprof/index.html
pypprof/net_http.py
pypprof/profile_pb2.py
pypprof/thread_profiler.py
pypprof.egg-info/PKG-INFO
pypprof.egg-info/SOURCES.txt
pypprof.egg-info/dependency_links.txt
pypprof.egg-info/requires.txt
pypprof.egg-info/top_level.txt
test/test_net_http.py