Metadata-Version: 2.1
Name: pypprof
Version: 0.0.1
Summary: Python profiler endpoints like Go's net/http/pprof.
Home-page: http://github.com/timpalpant/pypprof
Author: Timothy Palpant
Author-email: tim@palpant.us
License: LGPLv3
Project-URL: Source, https://github.com/timpalpant/pypprof
Project-URL: Tracker, https://github.com/timpalpant/pypprof/issues
Keywords: profiling performance
Platform: Mac OS X
Platform: POSIX
Classifier: Development Status :: 2 - Pre-Alpha
Classifier: Intended Audience :: Developers
Classifier: License :: OSI Approved :: GNU Lesser General Public License v3 (LGPLv3)
Classifier: Operating System :: POSIX
Classifier: Programming Language :: Python :: 2.7
Classifier: Programming Language :: Python :: 3.4
Classifier: Programming Language :: Python :: 3.5
Classifier: Programming Language :: Python :: 3.6
Classifier: Programming Language :: Python :: 3.7
Classifier: Programming Language :: Python :: Implementation :: CPython
Classifier: Topic :: Software Development :: Testing
Classifier: Topic :: Software Development :: Libraries :: Python Modules
